vcspack201/__init__.py
vcspack201/utils.py
vcspack201-0.1.dist-info/LICENSE.txt
vcspack201-0.1.dist-info/METADATA
vcspack201-0.1.dist-info/WHEEL
vcspack201-0.1.dist-info/top_level.txt
vcspack201-0.1.dist-info/RECORD
