Metadata-Version: 2.1
Name: vcspack201
Version: 0.1
Summary: vcspack utilities
Home-page: UNKNOWN
Author: vinay
Author-email: vinaygn@gmail.com
License: MIT
Platform: UNKNOWN
